iauditor_exporter/LICENSE
iauditor_exporter/README.md
iauditor_exporter/configs/config.yaml.sample
iauditor_exporter/docs/Install-python/mac.md
iauditor_exporter/docs/Install-python/overview.md
iauditor_exporter/docs/Install-python/windows.md
iauditor_exporter/docs/css/extra.css
iauditor_exporter/docs/images/brew.png
iauditor_exporter/docs/images/drag-and-drop-finder.gif
iauditor_exporter/docs/images/folder-in-finder.png
iauditor_exporter/docs/images/logo.svg
iauditor_exporter/docs/images/powerbi.png
iauditor_exporter/docs/images/spotlight-terminal.png
iauditor_exporter/docs/images/windows-python-site.png
iauditor_exporter/docs/index.md
iauditor_exporter/docs/install-intros/detailed-install.md
iauditor_exporter/docs/install-intros/docker.md
iauditor_exporter/docs/install-intros/introduction.md
iauditor_exporter/docs/install-intros/linux-install.md
iauditor_exporter/docs/install-intros/quick-install.md
iauditor_exporter/docs/install-intros/upgrading.md
iauditor_exporter/docs/javascripts/extra.js
iauditor_exporter/docs/requirements.txt
iauditor_exporter/docs/script-download/git.md
iauditor_exporter/docs/script-download/manual-dl.md
iauditor_exporter/docs/script-running/export-options.md
iauditor_exporter/docs/script-running/overview.md
iauditor_exporter/docs/script-setup/config.md
iauditor_exporter/docs/script-setup/configs-and-last-successful.md
iauditor_exporter/docs/script-setup/installing-packages.md
iauditor_exporter/docs/script-setup/mysql.md
iauditor_exporter/docs/script-setup/other-databases.md
iauditor_exporter/docs/understanding-the-data/csv-or-sql.md
iauditor_exporter/docs/understanding-the-data/datastructure.md
iauditor_exporter/docs/understanding-the-data/overview.md
iauditor_exporter/docs/understanding-the-data/the-model.md
iauditor_exporter/exporter.py
iauditor_exporter/modules/__init__.py
iauditor_exporter/modules/actions.py
iauditor_exporter/modules/csvExporter.py
iauditor_exporter/modules/exporters.py
iauditor_exporter/modules/global_variables.py
iauditor_exporter-1.7.7.dist-info/entry_points.txt
iauditor_exporter-1.7.7.dist-info/WHEEL
iauditor_exporter-1.7.7.dist-info/METADATA
iauditor_exporter-1.7.7.dist-info/RECORD
